<!-- Pedestrian Actors for Intersection -->
<!-- Add this section to your intersection.world file before </world> -->

<include><name>pedestrian_north_1</name><pose>-8 14 0 0 0 -1.57</pose><uri>model://DoctorFemaleWalk</uri><plugin filename="libgazebo_ros_actor_plugin.so" name="gazebo_ros_actor_plugin::GazeboRosActorCommand"><follow_mode>path</follow_mode><vel_topic>/pedestrian_north_1/cmd_vel</vel_topic><path_topic>/pedestrian_north_1/cmd_path</path_topic><animation_factor>4.0</animation_factor><linear_tolerance>0.1</linear_tolerance><linear_velocity>1.0</linear_velocity><angular_tolerance>0.0872</angular_tolerance><angular_velocity>2.5</angular_velocity><default_rotation>1.57</default_rotation></plugin></include>

<include><name>pedestrian_north_2</name><pose>8 14 0 0 0 1.57</pose><uri>model://DoctorFemaleWalk</uri><plugin filename="libgazebo_ros_actor_plugin.so" name="gazebo_ros_actor_plugin::GazeboRosActorCommand"><follow_mode>path</follow_mode><vel_topic>/pedestrian_north_2/cmd_vel</vel_topic><path_topic>/pedestrian_north_2/cmd_path</path_topic><animation_factor>4.0</animation_factor><linear_tolerance>0.1</linear_tolerance><linear_velocity>1.0</linear_velocity><angular_tolerance>0.0872</angular_tolerance><angular_velocity>2.5</angular_velocity><default_rotation>1.57</default_rotation></plugin></include>

<include><name>pedestrian_south_1</name><pose>-8 -14 0 0 0 -1.57</pose><uri>model://DoctorFemaleWalk</uri><plugin filename="libgazebo_ros_actor_plugin.so" name="gazebo_ros_actor_plugin::GazeboRosActorCommand"><follow_mode>path</follow_mode><vel_topic>/pedestrian_south_1/cmd_vel</vel_topic><path_topic>/pedestrian_south_1/cmd_path</path_topic><animation_factor>4.0</animation_factor><linear_tolerance>0.1</linear_tolerance><linear_velocity>1.0</linear_velocity><angular_tolerance>0.0872</angular_tolerance><angular_velocity>2.5</angular_velocity><default_rotation>1.57</default_rotation></plugin></include>

<include><name>pedestrian_south_2</name><pose>8 -14 0 0 0 1.57</pose><uri>model://DoctorFemaleWalk</uri><plugin filename="libgazebo_ros_actor_plugin.so" name="gazebo_ros_actor_plugin::GazeboRosActorCommand"><follow_mode>path</follow_mode><vel_topic>/pedestrian_south_2/cmd_vel</vel_topic><path_topic>/pedestrian_south_2/cmd_path</path_topic><animation_factor>4.0</animation_factor><linear_tolerance>0.1</linear_tolerance><linear_velocity>1.0</linear_velocity><angular_tolerance>0.0872</angular_tolerance><angular_velocity>2.5</angular_velocity><default_rotation>1.57</default_rotation></plugin></include>

<include><name>pedestrian_east_1</name><pose>14 -8 0 0 0 3.14</pose><uri>model://DoctorFemaleWalk</uri><plugin filename="libgazebo_ros_actor_plugin.so" name="gazebo_ros_actor_plugin::GazeboRosActorCommand"><follow_mode>path</follow_mode><vel_topic>/pedestrian_east_1/cmd_vel</vel_topic><path_topic>/pedestrian_east_1/cmd_path</path_topic><animation_factor>4.0</animation_factor><linear_tolerance>0.1</linear_tolerance><linear_velocity>1.0</linear_velocity><angular_tolerance>0.0872</angular_tolerance><angular_velocity>2.5</angular_velocity><default_rotation>1.57</default_rotation></plugin></include>

<include><name>pedestrian_east_2</name><pose>14 8 0 0 0 0</pose><uri>model://DoctorFemaleWalk</uri><plugin filename="libgazebo_ros_actor_plugin.so" name="gazebo_ros_actor_plugin::GazeboRosActorCommand"><follow_mode>path</follow_mode><vel_topic>/pedestrian_east_2/cmd_vel</vel_topic><path_topic>/pedestrian_east_2/cmd_path</path_topic><animation_factor>4.0</animation_factor><linear_tolerance>0.1</linear_tolerance><linear_velocity>1.0</linear_velocity><angular_tolerance>0.0872</angular_tolerance><angular_velocity>2.5</angular_velocity><default_rotation>1.57</default_rotation></plugin></include>

<include><name>pedestrian_west_1</name><pose>-14 -8 0 0 0 3.14</pose><uri>model://DoctorFemaleWalk</uri><plugin filename="libgazebo_ros_actor_plugin.so" name="gazebo_ros_actor_plugin::GazeboRosActorCommand"><follow_mode>path</follow_mode><vel_topic>/pedestrian_west_1/cmd_vel</vel_topic><path_topic>/pedestrian_west_1/cmd_path</path_topic><animation_factor>4.0</animation_factor><linear_tolerance>0.1</linear_tolerance><linear_velocity>1.0</linear_velocity><angular_tolerance>0.0872</angular_tolerance><angular_velocity>2.5</angular_velocity><default_rotation>1.57</default_rotation></plugin></include>

<include><name>pedestrian_west_2</name><pose>-14 8 0 0 0 0</pose><uri>model://DoctorFemaleWalk</uri><plugin filename="libgazebo_ros_actor_plugin.so" name="gazebo_ros_actor_plugin::GazeboRosActorCommand"><follow_mode>path</follow_mode><vel_topic>/pedestrian_west_2/cmd_vel</vel_topic><path_topic>/pedestrian_west_2/cmd_path</path_topic><animation_factor>4.0</animation_factor><linear_tolerance>0.1</linear_tolerance><linear_velocity>1.0</linear_velocity><angular_tolerance>0.0872</angular_tolerance><angular_velocity>2.5</angular_velocity><default_rotation>1.57</default_rotation></plugin></include>